cubicweb_seda/__init__.py
cubicweb_seda/__pkginfo__.py
cubicweb_seda/dataimport.py
cubicweb_seda/hooks.py
cubicweb_seda/makefile
cubicweb_seda/site_cubicweb.py
cubicweb_seda/testutils.py
cubicweb_seda/uiprops.py
cubicweb_seda/xsd.py
cubicweb_seda/xsd2concepts.py
cubicweb_seda/xsd2entities.py
cubicweb_seda/xsd2uicfg.py
cubicweb_seda/xsd2yams.py
cubicweb_seda/data/cubes.editionext.js
cubicweb_seda/data/cubes.jqtree.css
cubicweb_seda/data/cubes.jqtree.js
cubicweb_seda/data/cubes.seda.css
cubicweb_seda/data/cubes.seda.form.js
cubicweb_seda/data/cubes.seda.js
cubicweb_seda/data/cubes.skoscomplete.js
cubicweb_seda/data/jqtree.css
cubicweb_seda/data/tree.jquery.js
cubicweb_seda/entities/__init__.py
cubicweb_seda/entities/custom.py
cubicweb_seda/entities/diag.py
cubicweb_seda/entities/generated.py
cubicweb_seda/entities/html_generation.py
cubicweb_seda/entities/itree.py
cubicweb_seda/entities/profile_generation.py
cubicweb_seda/i18n/en.po
cubicweb_seda/i18n/fr.po
cubicweb_seda/i18n/static-messages.pot
cubicweb_seda/migration/0.10.4_Any.py
cubicweb_seda/migration/0.10.5_Any.py
cubicweb_seda/migration/0.10.6_Any.py
cubicweb_seda/migration/0.11.0_Any.py
cubicweb_seda/migration/0.12.0_Any.py
cubicweb_seda/migration/0.13.0_Any.py
cubicweb_seda/migration/0.17.7_Any.py
cubicweb_seda/migration/0.17.8_Any.py
cubicweb_seda/migration/0.5.1_Any.py
cubicweb_seda/migration/0.6.0_Any.py
cubicweb_seda/migration/0.8.0_Any.py
cubicweb_seda/migration/0.9.0_Any.py
cubicweb_seda/migration/0.9.1_Any.py
cubicweb_seda/migration/2.2.0_Any.py
cubicweb_seda/migration/postcreate.py
cubicweb_seda/migration/data/access_control.csv
cubicweb_seda/migration/data/classification_levels.csv
cubicweb_seda/migration/data/code_keyword_type.csv
cubicweb_seda/migration/data/digest_algorithms.csv
cubicweb_seda/migration/data/dissemination.csv
cubicweb_seda/migration/data/document_type_code.csv
cubicweb_seda/migration/data/dua.csv
cubicweb_seda/migration/data/encodings.csv
cubicweb_seda-2.4.1.dist-info/METADATA
cubicweb_seda-2.4.1.dist-info/WHEEL
cubicweb_seda-2.4.1.dist-info/entry_points.txt
cubicweb_seda-2.4.1.dist-info/top_level.txt
cubicweb_seda-2.4.1.dist-info/RECORD
