Metadata-Version: 2.1
Name: cubicweb-seda
Version: 2.4.1
Summary: Data Exchange Standard for Archival
Home-page: https://forge.extranet.logilab.fr/cubicweb/cubes/cubicweb-seda
Author: LOGILAB S.A. (Paris, FRANCE)
Author-email: contact@logilab.fr
License: LGPL
Classifier: Environment :: Web Environment
Classifier: Framework :: CubicWeb
Classifier: Programming Language :: Python
Classifier: Programming Language :: JavaScript
Requires-Dist: cubicweb[postgresql]<5.0,>=4.0.0
Requires-Dist: cubicweb-web<2.0.0,>=1.1.0
Requires-Dist: cubicweb-eac==0.10.0
Requires-Dist: cubicweb-skos>=3.1.0
Requires-Dist: cubicweb-compound>=1.0.0
Requires-Dist: cubicweb-relationwidget>=0.10
Requires-Dist: cubicweb-squareui>=2.0
Requires-Dist: cubicweb-geocoding>=1.0
Requires-Dist: pyxst>=0.3.2
Requires-Dist: rdflib>=4.1
